fhir/__build__
fhir/__init__.py
fhir/_version.py
fhir/model/__init__.py
fhir/model/_base64binary.py
fhir/model/_boolean.py
fhir/model/_canonical.py
fhir/model/_code.py
fhir/model/_date.py
fhir/model/_datetime.py
fhir/model/_decimal.py
fhir/model/_id.py
fhir/model/_instant.py
fhir/model/_integer.py
fhir/model/_markdown.py
fhir/model/_oid.py
fhir/model/_positiveint.py
fhir/model/_string.py
fhir/model/_time.py
fhir/model/_unsignedint.py
fhir/model/_uri.py
fhir/model/_url.py
fhir/model/_uuid.py
fhir/model/_xhtml.py
fhir/model/address.py
fhir/model/annotation.py
fhir/model/attachment.py
fhir/model/backboneelement.py
fhir/model/bundle.py
fhir/model/codeableconcept.py
fhir/model/coding.py
fhir/model/composition.py
fhir/model/contactdetail.py
fhir/model/contactpoint.py
fhir/model/domainresource.py
fhir/model/dosage.py
fhir/model/duration.py
fhir/model/encounter.py
fhir/model/episodeofcare.py
fhir/model/humanname.py
fhir/model/identifier.py
fhir/model/medication.py
fhir/model/medicationrequest.py
fhir/model/meta.py
fhir/model/narrative.py
fhir/model/observation.py
fhir/model/operationoutcome.py
fhir/model/patient.py
fhir/model/period.py
fhir/model/quantity.py
fhir/model/questionnaire.py
fhir/model/questionnaireresponse.py
fhir/model/range.py
fhir/model/ratio.py
fhir/model/reference.py
fhir/model/resource.py
fhir/model/sampleddata.py
fhir/model/signature.py
fhir/model/timing.py
fhir/model/usagecontext.py
fhir/model/valueset.py
fhir3/__init__.py
fhir3/client/__init__.py
fhir3/model/__init__.py
fhir3/model/_base64binary.py
fhir3/model/_boolean.py
fhir3/model/_code.py
fhir3/model/_date.py
fhir3/model/_datetime.py
fhir3/model/_decimal.py
fhir3/model/_id.py
fhir3/model/_instant.py
fhir3/model/_integer.py
fhir3/model/_markdown.py
fhir3/model/_oid.py
fhir3/model/_positiveint.py
fhir3/model/_string.py
fhir3/model/_time.py
fhir3/model/_unsignedint.py
fhir3/model/_uri.py
fhir3/model/_uuid.py
fhir3/model/_xhtml.py
fhir3/model/address.py
fhir3/model/attachment.py
py_fhir-0.1.1a5.dist-info/METADATA
py_fhir-0.1.1a5.dist-info/WHEEL
py_fhir-0.1.1a5.dist-info/top_level.txt
py_fhir-0.1.1a5.dist-info/RECORD
