Metadata-Version: 2.1
Name: py-fhir
Version: 0.1.1a5
Summary: FHIR classes for Python
Home-page: https://github.com/mellesies/py-fhir
License: UNKNOWN
Platform: UNKNOWN
Requires-Python: >=3
Requires-Dist: python-dateutil
Requires-Dist: formencode
Requires-Dist: jsondiff
Requires-Dist: packaging
Requires-Dist: pyyaml
Requires-Dist: termcolor
Requires-Dist: xmldiff
Provides-Extra: dev
Requires-Dist: twine ; extra == 'dev'
